.gitignore
CODE_OF_CONDUCT.md
CONTRIBUTING.md
LICENSE
Makefile
README.md
pyproject.toml
setup.cfg
.github/pull_request_template.md
.github/ISSUE_TEMPLATE/bug_report.md
.github/ISSUE_TEMPLATE/feature_request.md
.github/workflows/coverage.yml
.github/workflows/publish_release.yml
.github/workflows/style.yml
docs/DOC_README.md
docs/Makefile
docs/conf.py
docs/getting_started.rst
docs/index.rst
docs/make.bat
docs/requirements.txt
docs/_static/ZapataCLA.pdf
docs/_static/favicon.ico
docs/_static/orquestra.png
docs/examples/vqe/results.png
docs/examples/vqe/run_workflow.py
docs/examples/vqe/visualize_results.py
docs/examples/vqe/workflow_defs.py
docs/quantum/index.rst
docs/quantum/examples/__init__.py
docs/quantum/examples/guides/circuit_runners_guide.py
docs/quantum/examples/guides/circuits_guide.py
docs/quantum/examples/guides/estimators_guide.py
docs/quantum/examples/guides/interfaces_guide.py
docs/quantum/examples/guides/mock_ansatz.py
docs/quantum/examples/guides/optimizers.py
docs/quantum/examples/guides/vqa_guide.py
docs/quantum/examples/tests/__init__.py
docs/quantum/examples/tests/guides/__init__.py
docs/quantum/examples/tests/guides/test_circuit_runners_guide.py
docs/quantum/examples/tests/guides/test_circuits_guide.py
docs/quantum/examples/tests/guides/test_estimators_guide.py
docs/quantum/examples/tests/guides/test_mock_ansatz.py
docs/quantum/examples/tests/tutorials/__init__.py
docs/quantum/examples/tests/tutorials/test_bell_state.py
docs/quantum/examples/tests/tutorials/test_orqviz.py
docs/quantum/examples/tests/tutorials/test_qaoa_maxcut.py
docs/quantum/examples/tests/tutorials/test_superdense_coding.py
docs/quantum/examples/tutorials/bell_state.py
docs/quantum/examples/tutorials/orqviz.py
docs/quantum/examples/tutorials/qaoa_maxcut.py
docs/quantum/examples/tutorials/superdense_coding.py
docs/quantum/guides/circuit_runners.rst
docs/quantum/guides/circuits.rst
docs/quantum/guides/contributing.rst
docs/quantum/guides/index.rst
src/orquestra_core.egg-info/PKG-INFO
src/orquestra_core.egg-info/SOURCES.txt
src/orquestra_core.egg-info/dependency_links.txt
src/orquestra_core.egg-info/not-zip-safe
src/orquestra_core.egg-info/requires.txt
src/orquestra_core.egg-info/top_level.txt
