Metadata-Version: 2.1
Name: orquestra-core
Version: 0.10.0
Summary: "Orquestra Core meta-package"
Home-page: https://github.com/zapatacomputing/orquestra-core
Author: Zapata Computing Inc.
Author-email: info@zapatacomputing.com,
Classifier: Programming Language :: Python :: 3
Classifier: Operating System :: OS Independent
Classifier: License :: OSI Approved :: Apache Software License
Classifier: Topic :: Scientific/Engineering
Requires-Python: !=3.9.7,<3.11,>=3.8
Provides-Extra: dev
Provides-Extra: qulacs
Provides-Extra: qiskit
Provides-Extra: cirq
Provides-Extra: braket
Provides-Extra: forest
Provides-Extra: all
Provides-Extra: orqviz
License-File: LICENSE
